[
    {
        "party": "NPP",
        "candidate": "ANURA KUMARA DISSANAYAKE",
        "votes": "36,555",
        "percentage": "43.93%"
    },
    {
        "party": "SJB",
        "candidate": "SAJITH PREMADASA",
        "votes": "26,879",
        "percentage": "32.3%"
    },
    {
        "party": "IND16",
        "candidate": "RANIL WICKREMESINGHE",
        "votes": "14,217",
        "percentage": "17.09%"
    },
    {
        "party": "SLPP",
        "candidate": "NAMAL RAJAPAKSA",
        "votes": "3,142",
        "percentage": "3.78%"
    },
    {
        "party": "SLCP",
        "candidate": "DILITH JAYAWEERA",
        "votes": "676",
        "percentage": "0.81%"
    },
    {
        "party": "IND4",
        "candidate": "K.K. PIYADASA",
        "votes": "189",
        "percentage": "0.23%"
    },
    {
        "party": "IND13",
        "candidate": "DISSANAYAKA MUDIYANSELAGE BANDARANAYAKE",
        "votes": "149",
        "percentage": "0.18%"
    },
    {
        "party": "IND12",
        "candidate": "SARATH FONSEKA",
        "votes": "116",
        "percentage": "0.14%"
    },
    {
        "party": "DUNF",
        "candidate": "AGAMPODI PRASANGA SURANJEEWA ANOJ DE SILVA",
        "votes": "112",
        "percentage": "0.13%"
    },
    {
        "party": "SBP",
        "candidate": "NAMAL RAJAPAKSHA",
        "votes": "107",
        "percentage": "0.13%"
    },
    {
        "party": "IND11",
        "candidate": "ANURUDDHA POLGAMPALA",
        "votes": "104",
        "percentage": "0.12%"
    },
    {
        "party": "IND5",
        "candidate": "SARATH KEERTHIRATHNA",
        "votes": "103",
        "percentage": "0.12%"
    },
    {
        "party": "APP",
        "candidate": "K.R. KRISHAN",
        "votes": "98",
        "percentage": "0.12%"
    },
    {
        "party": "JPF",
        "candidate": "WIJEYADASA RAJAPAKSHE",
        "votes": "96",
        "percentage": "0.12%"
    },
    {
        "party": "NSSP",
        "candidate": "PRIYANTHA WICKRAMASINGHE",
        "votes": "60",
        "percentage": "0.07%"
    },
    {
        "party": "SPF",
        "candidate": "NUWAN BOPEGE",
        "votes": "59",
        "percentage": "0.07%"
    },
    {
        "party": "IND1",
        "candidate": "AKMEEMANA DAYARATHANA THERO",
        "votes": "55",
        "percentage": "0.07%"
    },
    {
        "party": "RJA",
        "candidate": "AJANTHA DE ZOYSA",
        "votes": "47",
        "percentage": "0.06%"
    },
    {
        "party": "IND10",
        "candidate": "VICTOR PERERA",
        "votes": "47",
        "percentage": "0.06%"
    },
    {
        "party": "IND2",
        "candidate": "SIRIPALA AMARASINGHE",
        "votes": "45",
        "percentage": "0.05%"
    },
    {
        "party": "USP",
        "candidate": "SIRITUNGA JAYASURIYA",
        "votes": "42",
        "percentage": "0.05%"
    },
    {
        "party": "DUA",
        "candidate": "ABUBAKAR MOHAMED INFAS",
        "votes": "34",
        "percentage": "0.04%"
    },
    {
        "party": "JSP",
        "candidate": "BATHTHARAMULLE SEELARATHANA THERO",
        "votes": "33",
        "percentage": "0.04%"
    },
    {
        "party": "IND6",
        "candidate": "K.A. KULARATNA",
        "votes": "29",
        "percentage": "0.03%"
    },
    {
        "party": "NDF",
        "candidate": "SARATH BANDARANAYAKE",
        "votes": "28",
        "percentage": "0.03%"
    },
    {
        "party": "IND14",
        "candidate": "PEMASIRI MANAGE",
        "votes": "25",
        "percentage": "0.03%"
    },
    {
        "party": "SLSP",
        "candidate": "MAHINDA DEWAGE",
        "votes": "23",
        "percentage": "0.03%"
    },
    {
        "party": "IND15",
        "candidate": "ANURUDDHA ROSHAN RANASINGHE",
        "votes": "18",
        "percentage": "0.02%"
    },
    {
        "party": "AJP",
        "candidate": "KEERTHIE WICKRAMARATNE",
        "votes": "17",
        "percentage": "0.02%"
    },
    {
        "party": "SEP",
        "candidate": "PANI WIJESIRIWARDENA",
        "votes": "17",
        "percentage": "0.02%"
    },
    {
        "party": "IND7",
        "candidate": "PALLIMULLA KAPUGAMAGE ANURA SIDNEY JAYARATHNA",
        "votes": "16",
        "percentage": "0.02%"
    },
    {
        "party": "NIF",
        "candidate": "OSHALA HERATH",
        "votes": "15",
        "percentage": "0.02%"
    },
    {
        "party": "UNFF",
        "candidate": "LALITH DE SILVA",
        "votes": "11",
        "percentage": "0.01%"
    },
    {
        "party": "IND9",
        "candidate": "ARIYANETHIRAN PAKKIYASELVAM",
        "votes": "11",
        "percentage": "0.01%"
    },
    {
        "party": "SLLP",
        "candidate": "A.S.P. LIYANAGE",
        "votes": "9",
        "percentage": "0.01%"
    },
    {
        "party": "IND8",
        "candidate": "MYLVAGANAM THILAKARAJAH",
        "votes": "8",
        "percentage": "0.01%"
    },
    {
        "party": "ELPP",
        "candidate": "JANAKA RATNAYAKE",
        "votes": "7",
        "percentage": "0.01%"
    },
    {
        "party": "NSU",
        "candidate": "SARATH MANAMENDRA",
        "votes": "5",
        "percentage": "0.01%"
    }
]